epics_appimage/__init__.py
epics_appimage/_AppImage/squashfs-root/.DirIcon
epics_appimage/_AppImage/squashfs-root/AppRun
epics_appimage/_AppImage/squashfs-root/EPICS_Logo-192x192.png
epics_appimage/_AppImage/squashfs-root/entrypoint.desktop
epics_appimage/_AppImage/squashfs-root/dbd/softIoc.dbd
epics_appimage/_AppImage/squashfs-root/dbd/softIocPVA.dbd
epics_appimage/_AppImage/squashfs-root/usr/bin/acctst
epics_appimage/_AppImage/squashfs-root/usr/bin/antelope
epics_appimage/_AppImage/squashfs-root/usr/bin/ascheck
epics_appimage/_AppImage/squashfs-root/usr/bin/caConnTest
epics_appimage/_AppImage/squashfs-root/usr/bin/caEventRate
epics_appimage/_AppImage/squashfs-root/usr/bin/caRepeater
epics_appimage/_AppImage/squashfs-root/usr/bin/ca_test
epics_appimage/_AppImage/squashfs-root/usr/bin/caget
epics_appimage/_AppImage/squashfs-root/usr/bin/cainfo
epics_appimage/_AppImage/squashfs-root/usr/bin/camonitor
epics_appimage/_AppImage/squashfs-root/usr/bin/caput
epics_appimage/_AppImage/squashfs-root/usr/bin/casw
epics_appimage/_AppImage/squashfs-root/usr/bin/catime
epics_appimage/_AppImage/squashfs-root/usr/bin/e_flex
epics_appimage/_AppImage/squashfs-root/usr/bin/iocLogServer
epics_appimage/_AppImage/squashfs-root/usr/bin/makeBpt
epics_appimage/_AppImage/squashfs-root/usr/bin/msi
epics_appimage/_AppImage/squashfs-root/usr/bin/p2p
epics_appimage/_AppImage/squashfs-root/usr/bin/pvcall
epics_appimage/_AppImage/squashfs-root/usr/bin/pvget
epics_appimage/_AppImage/squashfs-root/usr/bin/pvinfo
epics_appimage/_AppImage/squashfs-root/usr/bin/pvlist
epics_appimage/_AppImage/squashfs-root/usr/bin/pvmonitor
epics_appimage/_AppImage/squashfs-root/usr/bin/pvput
epics_appimage/_AppImage/squashfs-root/usr/bin/softIoc
epics_appimage/_AppImage/squashfs-root/usr/bin/softIocPVA
epics_appimage/_AppImage/squashfs-root/usr/lib/libCom.so.3.23.1
epics_appimage/_AppImage/squashfs-root/usr/lib/libca.so.4.14.4
epics_appimage/_AppImage/squashfs-root/usr/lib/libdbCore.so.3.23.1
epics_appimage-7.0.8.1.dist-info/LICENSE
epics_appimage-7.0.8.1.dist-info/METADATA
epics_appimage-7.0.8.1.dist-info/WHEEL
epics_appimage-7.0.8.1.dist-info/entry_points.txt
epics_appimage-7.0.8.1.dist-info/top_level.txt
epics_appimage-7.0.8.1.dist-info/RECORD
