Metadata-Version: 2.1
Name: epics-appimage
Version: 7.0.8.1
Summary: AppImages built from EPICS base
Home-page: https://github.com/archman/epics-appimage
Author: Tong Zhang
Author-email: zhangt@frib.msu.edu
License: GPLv3
Download-URL: https://pypi.org/project/epics-appimage
Platform: UNKNOWN
Classifier: License :: OSI Approved :: GNU General Public License v3 (GPLv3)
Classifier: Topic :: Software Development
Classifier: Topic :: Scientific/Engineering
Classifier: Operating System :: POSIX :: Linux
